kaiser/__init__.py
kaiser-0.1.dist-info/METADATA
kaiser-0.1.dist-info/WHEEL
kaiser-0.1.dist-info/top_level.txt
kaiser-0.1.dist-info/RECORD
