Metadata-Version: 2.1
Name: kaiser
Version: 0.1
Summary: first iteration
Home-page: https://github.com/SohamPathak/kaiser
Author: SohamPathak
Author-email: sohamkiit636@gmail.com
License: None
Platform: UNKNOWN
